LICENSE
MANIFEST.in
README.rst
changelog.rst
setup.py
tinflask/.handlers.py.swp
tinflask/.web.py.swp
tinflask/__init__.py
tinflask/handlers.py
tinflask/web.py
tinflask.egg-info/PKG-INFO
tinflask.egg-info/SOURCES.txt
tinflask.egg-info/dependency_links.txt
tinflask.egg-info/requires.txt
tinflask.egg-info/top_level.txt
tinflask/__pycache__/__init__.cpython-34.pyc
tinflask/__pycache__/etcd.cpython-34.pyc
tinflask/__pycache__/handlers.cpython-34.pyc
tinflask/__pycache__/keystore.cpython-34.pyc
tinflask/__pycache__/web.cpython-34.pyc