Metadata-Version: 1.1
Name: tinflask
Version: 0.0.2
Summary: Simple wrapper around flask that uses environment variables for host, port, endpoint prefix. Also uses the py-hancock library for the ability to sign endpoints. Endpoints for `time`, `ping`, and `status` are automatically added as well.
Home-page: http://pypi.python.org/pypi/tinflask
Author: Justin Wilson
Author-email: justinwilson1@gmail.com
License: Simplified BSD
Platform: UNKNOWN
Classifier: Development Status :: 4 - Beta
Classifier: Intended Audience :: Developers
Classifier: Topic :: Utilities
Classifier: License :: OSI Approved :: BSD License
Classifier: Natural Language :: English
Classifier: Programming Language :: Python
Classifier: Programming Language :: Python :: 3.2
Classifier: Programming Language :: Python :: 3.3
Classifier: Programming Language :: Python :: 3.4
